p4lantir/__init__.py
p4lantir/__main__.py
p4lantir/config.py
p4lantir/utils.py
p4lantir/mitm/__init__.py
p4lantir/mitm/mitm_utils.py
p4lantir/mitm/proxy_server.py
p4lantir/widgets/__init__.py
p4lantir/widgets/app_ui.py
p4lantir/widgets/enter_screen.py
p4lantir/widgets/logger.py
p4lantir-1.0.2.dist-info/METADATA
p4lantir-1.0.2.dist-info/WHEEL
p4lantir-1.0.2.dist-info/entry_points.txt
p4lantir-1.0.2.dist-info/licenses/LICENSE.TXT
p4lantir-1.0.2.dist-info/RECORD
