Metadata-Version: 2.4
Name: p4lantir
Version: 1.0.2
Summary: MiTM over TCP to intercept and manipulate flow
Project-URL: Repository, https://github.com/acmo0/p4lantir.git
Author: acmo0
License-Expression: GPL-3.0-or-later
License-File: LICENSE.TXT
Keywords: TCP,man-in-the-middle,mitm,proxy,textual
Classifier: Development Status :: 4 - Beta
Classifier: Environment :: Console
Classifier: Intended Audience :: Education
Classifier: Intended Audience :: Science/Research
Classifier: Intended Audience :: System Administrators
Requires-Python: >=3.9
Requires-Dist: astroid==3.3.11
Requires-Dist: colorlog==6.9.0
Requires-Dist: dill==0.4.0
Requires-Dist: isort==6.0.1
Requires-Dist: linkify-it-py==2.0.3
Requires-Dist: markdown-it-py==4.0.0
Requires-Dist: mccabe==0.7.0
Requires-Dist: mdit-py-plugins==0.5.0
Requires-Dist: mdurl==0.1.2
Requires-Dist: platformdirs==4.3.8
Requires-Dist: pygments==2.19.2
Requires-Dist: rich==14.1.0
Requires-Dist: textual==5.3.0
Requires-Dist: tomlkit==0.13.3
Requires-Dist: typing-extensions==4.14.1
Requires-Dist: uc-micro-py==1.0.3
